LICENSE
MANIFEST.in
README.md
setup.py
.idea/.gitignore
.idea/SoeasyPack.iml
.idea/misc.xml
.idea/modules.xml
.idea/vcs.xml
.idea/workspace.xml
.idea/inspectionProfiles/Project_Default.xml
.idea/inspectionProfiles/profiles_settings.xml
soeasypack/__init__.py
soeasypack.egg-info/PKG-INFO
soeasypack.egg-info/SOURCES.txt
soeasypack.egg-info/dependency_links.txt
soeasypack.egg-info/not-zip-safe
soeasypack.egg-info/requires.txt
soeasypack.egg-info/top_level.txt
soeasypack/core/__init__.py
soeasypack/core/ast_find_depend.py
soeasypack/core/easy_pack.py
soeasypack/core/my_logger.py
soeasypack/core/py_to_pyd.py
soeasypack/core/re_find_pkg.py
soeasypack/core/slimfile.py
soeasypack/dep_exe/Procmon64.exe
soeasypack/dep_exe/ProcmonConfiguration.pmc
soeasypack/dep_exe/go_env/go-winres.exe
soeasypack/dep_exe/go_env/go_py.go
soeasypack/dep_exe/go_env/go_py_embed.go
soeasypack/dep_exe/go_env/winres.json
soeasypack/dep_exe/go_env/bin/go.exe
soeasypack/dep_exe/go_env/pkg/include/asm_amd64.h
soeasypack/dep_exe/go_env/pkg/include/asm_ppc64x.h
soeasypack/dep_exe/go_env/pkg/include/funcdata.h
soeasypack/dep_exe/go_env/pkg/include/textflag.h
soeasypack/dep_exe/go_env/pkg/tool/windows_amd64/asm.exe
soeasypack/dep_exe/go_env/pkg/tool/windows_amd64/compile.exe
soeasypack/dep_exe/go_env/pkg/tool/windows_amd64/link.exe
soeasypack/dep_exe/go_env/src/archive/zip/reader.go
soeasypack/dep_exe/go_env/src/archive/zip/register.go
soeasypack/dep_exe/go_env/src/archive/zip/struct.go
soeasypack/dep_exe/go_env/src/archive/zip/writer.go
soeasypack/dep_exe/go_env/src/bufio/bufio.go
soeasypack/dep_exe/go_env/src/bufio/scan.go
soeasypack/dep_exe/go_env/src/bytes/boundary_test.go
soeasypack/dep_exe/go_env/src/bytes/buffer.go
soeasypack/dep_exe/go_env/src/bytes/buffer_test.go
soeasypack/dep_exe/go_env/src/bytes/bytes.go
soeasypack/dep_exe/go_env/src/bytes/bytes_js_wasm_test.go
soeasypack/dep_exe/go_env/src/bytes/bytes_test.go
soeasypack/dep_exe/go_env/src/bytes/compare_test.go
soeasypack/dep_exe/go_env/src/bytes/example_test.go
soeasypack/dep_exe/go_env/src/bytes/export_test.go
soeasypack/dep_exe/go_env/src/bytes/reader.go
soeasypack/dep_exe/go_env/src/bytes/reader_test.go
