Metadata-Version: 2.4
Name: soeasypack
Version: 0.9.12
Summary: 简易精准打包python项目和依赖环境 Easy and precise packaging of python projects and dependencies
Home-page: https://github.com/XMQSVIP/SoEasyPack
Author: xmqsvip
Author-email: xmqsvip@qq.com
License: MIT
Keywords: soeasypack,packaging,pyinstaller,py2exe,cxfreeze
Classifier: Programming Language :: Python :: 3
License-File: LICENSE
Requires-Dist: setuptools
Requires-Dist: objectgraph
Requires-Dist: Cython
Dynamic: author
Dynamic: author-email
Dynamic: classifier
Dynamic: description
Dynamic: description-content-type
Dynamic: home-page
Dynamic: keywords
Dynamic: license
Dynamic: license-file
Dynamic: requires-dist
Dynamic: summary
